tox_toml_fmt/__init__.py
tox_toml_fmt/__main__.py
tox_toml_fmt/_lib.pyi
tox_toml_fmt/_lib.pypy310-pp73-x86_64-linux-gnu.so
tox_toml_fmt/py.typed
tox_toml_fmt-1.3.0.dist-info/METADATA
tox_toml_fmt-1.3.0.dist-info/WHEEL
tox_toml_fmt-1.3.0.dist-info/entry_points.txt
tox_toml_fmt-1.3.0.dist-info/licenses/LICENSE.txt
tox_toml_fmt-1.3.0.dist-info/RECORD
