Metadata-Version: 2.4
Name: tox-toml-fmt
Version: 1.3.0
Classifier: License :: OSI Approved :: MIT License
Classifier: Operating System :: OS Independent
Classifier: Programming Language :: Python
Classifier: Programming Language :: Python :: 3 :: Only
Classifier: Programming Language :: Python :: 3.10
Classifier: Programming Language :: Python :: 3.11
Classifier: Programming Language :: Python :: 3.12
Classifier: Programming Language :: Python :: 3.13
Classifier: Programming Language :: Python :: 3.14
Requires-Dist: toml-fmt-common==1.2
License-File: LICENSE.txt
Summary: Format your pyproject.toml file
Keywords: format,pyproject
Author-email: Bernat Gabor <gaborjbernat@gmail.com>
Requires-Python: >=3.10
Project-URL: Bug Tracker, https://github.com/tox-dev/toml-fmt/issues
Project-URL: Changelog, https://github.com/tox-dev/toml-fmt/blob/main/tox-toml-fmt/CHANGELOG.md
Project-URL: Documentation, https://tox-toml-fmt.readthedocs.io/en/latest/
Project-URL: Source Code, https://github.com/tox-dev/toml-fmt/tree/main/tox-toml-fmt
